myth_channel_updater-0.1.0.data/scripts/mythchannels
mythchannels/__init__.py
mythchannels/arguments.py
mythchannels/backend.py
mythchannels/channel.py
mythchannels/rule.py
mythchannels/rules.py
mythchannels/xml.py
tests/__init__.py
tests/test_backend.py
tests/test_rule.py
myth_channel_updater-0.1.0.dist-info/LICENSE
myth_channel_updater-0.1.0.dist-info/METADATA
myth_channel_updater-0.1.0.dist-info/WHEEL
myth_channel_updater-0.1.0.dist-info/top_level.txt
myth_channel_updater-0.1.0.dist-info/RECORD
