Metadata-Version: 2.1
Name: myth-channel-updater
Version: 0.1.0
Summary: A script to help maintain the list of channels in MythTV.
Home-page: https://github.com/andrewjw/myth-channel-updater
Author: Andrew Wilkinson
Author-email: andrewjwilkinson@gmail.com
License: UNKNOWN
Platform: UNKNOWN
Classifier: Programming Language :: Python :: 3.8
Classifier: License :: OSI Approved :: GNU General Public License v3 (GPLv3)
Classifier: Operating System :: OS Independent
Requires-Python: >=3.8
Requires-Dist: coverage (==6.4.1)
Requires-Dist: pycodestyle (==2.8.0)
Requires-Dist: python-coveralls (==2.9.3)
Requires-Dist: python-semantic-release (==7.27.1)
Requires-Dist: pyyaml (==6.0)
Requires-Dist: requests (==2.28.1)
Requires-Dist: responses (==0.21.0)
